hirmeos_clients/__init__.py
hirmeos_clients/altmetrics.py
hirmeos_clients/tokens_api.py
hirmeos_clients/translator.py
hirmeos_clients/variables.py
hirmeos_clients-0.2.2.dist-info/licenses/LICENSE
hirmeos_clients-0.2.2.dist-info/METADATA
hirmeos_clients-0.2.2.dist-info/WHEEL
hirmeos_clients-0.2.2.dist-info/top_level.txt
hirmeos_clients-0.2.2.dist-info/RECORD
