Metadata-Version: 2.4
Name: hirmeos-clients
Version: 0.2.2
Summary: Python API clients for the OPERAS metrics
Author-email: Rowan Hatherley <rowan.hatherley@ubiquitypress.com>, Cristian Garcia <cristian.garcia@ubiquitypress.com>
Classifier: Programming Language :: Python :: 3
Classifier: License :: OSI Approved :: MIT License
Classifier: Operating System :: OS Independent
Requires-Python: <3.13,>=3.7
License-File: LICENSE
Requires-Dist: requests<3.0,>=2.0
Requires-Dist: PyJWT<=3.0,>=2.4
Dynamic: license-file
